G80SXM/__init__.py
G80SXM/FFTPanel.py
G80SXM/FilterPanel.py
G80SXM/FitPanel.py
G80SXM/GridPanel.py
G80SXM/gui.py
G80SXM/LineProfilePanel.py
G80SXM/MainPanel.py
G80SXM/nanonispyfit.py
G80SXM/Panel.py
G80SXM/STSPanel.py
xyz/Cu.xyz
xyz/DCA.xyz
xyz/HAT.xyz
xyz/HAT2CuPlanar.xyz
g80sxm-1.0.1.dist-info/entry_points.txt
g80sxm-1.0.1.dist-info/LICENSE
g80sxm-1.0.1.dist-info/METADATA
g80sxm-1.0.1.dist-info/WHEEL
g80sxm-1.0.1.dist-info/RECORD
