Metadata-Version: 2.1
Name: g80sxm
Version: 1.0.1
Summary: Analyse and create figures for Nanonis SPM data
License: MIT
Keywords: stm,python,scanning tunnelling microscopy,sts,sxm,spm,figures,analyse,analysis,plot
Author: Julian Ceddia
Author-email: jdceddia@gmail.com
Requires-Python: >=3.9,<4.0
Classifier: License :: OSI Approved :: MIT License
Classifier: Programming Language :: Python :: 3
Classifier: Programming Language :: Python :: 3.9
Classifier: Programming Language :: Python :: 3.10
Classifier: Programming Language :: Python :: 3.11
Classifier: Programming Language :: Python :: 3.12
Requires-Dist: ase
Requires-Dist: customtkinter
Requires-Dist: lmfit
Requires-Dist: matplotlib
Requires-Dist: matplotlib_scalebar
Requires-Dist: nanonispy2
Requires-Dist: numpy (<2)
Requires-Dist: scipy (<1.14)
Requires-Dist: tk
